impysonator
