Metadata-Version: 1.2
Name: impysonator
Version: 0.1.3
Summary: Seja Impessoal!
Home-page: http://github.com/guidiego/impysonator
Author: Guiherme Diego
Author-email: guilherme.albino.francisco@gmail.com
License: MIT
Project-URL: Bug Reports, https://github.com/guidiego/impysonator/issues
Project-URL: Source, https://github.com/guidiego/impysonator/
Keywords: python impessoal paper artigo revisão review
Platform: UNKNOWN
Classifier: Development Status :: 4 - Beta
Classifier: Topic :: Text Processing :: Linguistic
Classifier: Topic :: Utilities
Classifier: License :: OSI Approved :: MIT License
Classifier: Programming Language :: Python :: 3.6
Requires-Python: >=3.6
